honeybee_radiance_command/__init__.py
honeybee_radiance_command/_command.py
honeybee_radiance_command/_command_util.py
honeybee_radiance_command/_exception.py
honeybee_radiance_command/_typing.py
honeybee_radiance_command/cutil.py
honeybee_radiance_command/dcglare.py
honeybee_radiance_command/dctimestep.py
honeybee_radiance_command/evalglare.py
honeybee_radiance_command/falsecolor.py
honeybee_radiance_command/gendaylit.py
honeybee_radiance_command/gendaymtx.py
honeybee_radiance_command/gensky.py
honeybee_radiance_command/getinfo.py
honeybee_radiance_command/ies2rad.py
honeybee_radiance_command/oconv.py
honeybee_radiance_command/pcomb.py
honeybee_radiance_command/pcompos.py
honeybee_radiance_command/pcond.py
honeybee_radiance_command/pfilt.py
honeybee_radiance_command/pflip.py
honeybee_radiance_command/pinterp.py
honeybee_radiance_command/psign.py
honeybee_radiance_command/ra_gif.py
honeybee_radiance_command/ra_xyze.py
honeybee_radiance_command/rcalc.py
honeybee_radiance_command/rcollate.py
honeybee_radiance_command/rcontrib.py
honeybee_radiance_command/rfluxmtx.py
honeybee_radiance_command/rmtxop.py
honeybee_radiance_command/rpict.py
honeybee_radiance_command/rtrace.py
honeybee_radiance_command/options/__init__.py
honeybee_radiance_command/options/_optutil.py
honeybee_radiance_command/options/accelerad.py
honeybee_radiance_command/options/dcglare.py
honeybee_radiance_command/options/dctimestep.py
honeybee_radiance_command/options/evalglare.py
honeybee_radiance_command/options/falsecolor.py
honeybee_radiance_command/options/gendaylit.py
honeybee_radiance_command/options/gendaymtx.py
honeybee_radiance_command/options/gensky.py
honeybee_radiance_command/options/getinfo.py
honeybee_radiance_command/options/ies2rad.py
honeybee_radiance_command/options/oconv.py
honeybee_radiance_command/options/optionbase.py
honeybee_radiance_command/options/pcomb.py
honeybee_radiance_command/options/pcompos.py
honeybee_radiance_command/options/pcond.py
honeybee_radiance_command-1.23.0.dist-info/licenses/LICENSE
honeybee_radiance_command-1.23.0.dist-info/METADATA
honeybee_radiance_command-1.23.0.dist-info/WHEEL
honeybee_radiance_command-1.23.0.dist-info/top_level.txt
honeybee_radiance_command-1.23.0.dist-info/RECORD
